pypinyin_dict/__init__.py
pypinyin_dict/phrase_pinyin_data/__init__.py
pypinyin_dict/phrase_pinyin_data/cc_cedict.py
pypinyin_dict/phrase_pinyin_data/cc_cedict_0.py
pypinyin_dict/phrase_pinyin_data/cc_cedict_1.py
pypinyin_dict/phrase_pinyin_data/cc_cedict_2.py
pypinyin_dict/phrase_pinyin_data/cc_cedict_3.py
pypinyin_dict/phrase_pinyin_data/di.py
pypinyin_dict/phrase_pinyin_data/large_pinyin.py
pypinyin_dict/phrase_pinyin_data/large_pinyin_0.py
pypinyin_dict/phrase_pinyin_data/large_pinyin_1.py
pypinyin_dict/phrase_pinyin_data/large_pinyin_10.py
pypinyin_dict/phrase_pinyin_data/large_pinyin_2.py
pypinyin_dict/phrase_pinyin_data/large_pinyin_3.py
pypinyin_dict/phrase_pinyin_data/large_pinyin_4.py
pypinyin_dict/phrase_pinyin_data/large_pinyin_5.py
pypinyin_dict/phrase_pinyin_data/large_pinyin_6.py
pypinyin_dict/phrase_pinyin_data/large_pinyin_7.py
pypinyin_dict/phrase_pinyin_data/large_pinyin_8.py
pypinyin_dict/phrase_pinyin_data/large_pinyin_9.py
pypinyin_dict/phrase_pinyin_data/pinyin.py
pypinyin_dict/phrase_pinyin_data/zdic_cibs.py
pypinyin_dict/phrase_pinyin_data/zdic_cibs_0.py
pypinyin_dict/phrase_pinyin_data/zdic_cibs_1.py
pypinyin_dict/phrase_pinyin_data/zdic_cibs_2.py
pypinyin_dict/phrase_pinyin_data/zdic_cibs_3.py
pypinyin_dict/phrase_pinyin_data/zdic_cibs_4.py
pypinyin_dict/phrase_pinyin_data/zdic_cibs_5.py
pypinyin_dict/phrase_pinyin_data/zdic_cibs_6.py
pypinyin_dict/phrase_pinyin_data/zdic_cibs_7.py
pypinyin_dict/phrase_pinyin_data/zdic_cybs.py
pypinyin_dict/phrase_pinyin_data/zdic_cybs_0.py
pypinyin_dict/phrase_pinyin_data/zdic_cybs_1.py
pypinyin_dict/phrase_pinyin_data/zdic_cybs_2.py
pypinyin_dict/phrase_pinyin_data/zdic_cybs_3.py
pypinyin_dict/pinyin_data/__init__.py
pypinyin_dict/pinyin_data/cc_cedict.py
pypinyin_dict/pinyin_data/khanyupinlu.py
pypinyin_dict/pinyin_data/khanyupinyin.py
pypinyin_dict/pinyin_data/kmandarin_8105.py
pypinyin_dict/pinyin_data/ktghz2013.py
pypinyin_dict/pinyin_data/kxhc1983.py
pypinyin_dict/pinyin_data/pinyin.py
pypinyin_dict-0.9.0.dist-info/LICENSE
pypinyin_dict-0.9.0.dist-info/METADATA
pypinyin_dict-0.9.0.dist-info/WHEEL
pypinyin_dict-0.9.0.dist-info/top_level.txt
pypinyin_dict-0.9.0.dist-info/RECORD
