Metadata-Version: 2.2
Name: pypinyin-dict
Version: 0.9.0
Summary: 使用 pinyin-data 和 phrase-pinyin-data 中的拼音数据文件覆盖 pypinyin 中的自带拼音数据，实现只使用某个或某些拼音数据文件中的拼音数据的需求
Home-page: https://github.com/mozillazg/pypinyin-dict
Author: mozillazg
Author-email: mozillazg101@gmail.com
Project-URL: Bug Tracker, https://github.com/mozillazg/pypinyin-dict/issues
Classifier: Programming Language :: Python :: 2
Classifier: Programming Language :: Python :: 3
Classifier: License :: OSI Approved :: MIT License
Classifier: Operating System :: OS Independent
Requires-Python: >=2.6, !=3.0.*, !=3.1.*, !=3.2.*, <4
License-File: LICENSE
Requires-Dist: pypinyin
Dynamic: author
Dynamic: author-email
Dynamic: classifier
Dynamic: description
Dynamic: description-content-type
Dynamic: home-page
Dynamic: project-url
Dynamic: requires-dist
Dynamic: requires-python
Dynamic: summary
